airflow_providers_prima/__init__.py
airflow_providers_prima-0.0.1.dist-info/WHEEL
airflow_providers_prima-0.0.1.dist-info/METADATA
airflow_providers_prima-0.0.1.dist-info/RECORD
