Metadata-Version: 2.1
Name: airflow-providers-prima
Version: 0.0.1
Summary: python repository for commmons operators,hooks and utils for Apache Airflow
Author: sceriol
Author-email: simone.cerioli@prima.it
Requires-Python: >=3.9,<4.0
Classifier: Programming Language :: Python :: 3
Classifier: Programming Language :: Python :: 3.10
Classifier: Programming Language :: Python :: 3.9
